README.md
setup.py
pyflow/__init__.py
pyflow/flowlib.py
pyflow/flowlibwarped.py
pyflow/interactive_flow.py
pynpflow.egg-info/PKG-INFO
pynpflow.egg-info/SOURCES.txt
pynpflow.egg-info/dependency_links.txt
pynpflow.egg-info/not-zip-safe
pynpflow.egg-info/requires.txt
pynpflow.egg-info/top_level.txt