Metadata-Version: 1.0
Name: pynpflow
Version: 0.2
Summary: Optical flow library for python. 
Home-page: https://github.com/JuanFMontesinos/PyOF
Author: Juan Montesinos
Author-email: juanfelipe.montesinos@upf.edu
License: UNKNOWN
Platform: UNKNOWN
